datera_cinder/__init__.py
datera_cinder/datera_api21.py
datera_cinder/datera_api22.py
datera_cinder/datera_common.py
datera_cinder/datera_iscsi.py
datera_cinder/test_datera.py
datera_cinder-2019.6.4.1.dist-info/LICENSE
datera_cinder-2019.6.4.1.dist-info/METADATA
datera_cinder-2019.6.4.1.dist-info/WHEEL
datera_cinder-2019.6.4.1.dist-info/top_level.txt
datera_cinder-2019.6.4.1.dist-info/RECORD
