Metadata-Version: 2.1
Name: datera-cinder
Version: 2019.6.4.1
Summary: Datera OpenStack Cinder Driver
Home-page: https://github.com/Datera/cinder-driver/
Author: Datera Ecosystem Team
Author-email: support@datera.io
License: UNKNOWN
Download-URL: https://github.com/Datera/cinder-driver/tarball/v2019.6.4.1
Platform: UNKNOWN
Classifier: Programming Language :: Python :: 2
Classifier: Programming Language :: Python :: 3
Classifier: License :: OSI Approved :: Apache Software License
Classifier: Operating System :: OS Independent
Requires-Dist: dfs-sdk
